applicationcount/__init__.py
applicationcount/generate.py
count/__init__.py
count/count.py
applicationcount-0.0.3.dist-info/LICENSE
applicationcount-0.0.3.dist-info/METADATA
applicationcount-0.0.3.dist-info/WHEEL
applicationcount-0.0.3.dist-info/top_level.txt
applicationcount-0.0.3.dist-info/RECORD
