Metadata-Version: 2.1
Name: applicationcount
Version: 0.0.3
Summary: Get number of candidates that applied to the job. You can now generate passsword too.
Home-page: UNKNOWN
Author: Siddesh
Author-email: <mail@siddesh.com>
License: UNKNOWN
Keywords: python,job,application
Platform: UNKNOWN
Classifier: Development Status :: 1 - Planning
Classifier: Intended Audience :: Developers
Classifier: Programming Language :: Python :: 3
Classifier: Operating System :: Unix
Classifier: Operating System :: MacOS :: MacOS X
Classifier: Operating System :: Microsoft :: Windows
License-File: LICENSE
